pydebootstrap/__init__.py
pydebootstrap/config.py
pydebootstrap/pydebootstrap.py
pydebootstrap-1.2.2.dist-info/METADATA
pydebootstrap-1.2.2.dist-info/WHEEL
pydebootstrap-1.2.2.dist-info/top_level.txt
pydebootstrap-1.2.2.dist-info/RECORD
