Metadata-Version: 2.1
Name: pydebootstrap
Version: 1.2.2
Summary: Python wrapper for debootstrap
Home-page: http://github.com/dfoulks1/pydebootstrap
Author: Drew Foulks
Author-email: dfoulks@gmail.com
License: Apache v2 License
Platform: UNKNOWN
